cdjs-0.1.5.dist-info/METADATA
cdjs-0.1.5.dist-info/WHEEL
cdjs/__pycache__/__init__.cpython-36.pyc
cdjs/__init__.py
cdjs/cdjs.cpython-36m-x86_64-linux-gnu.so
cdjs-0.1.5.dist-info/RECORD
