Metadata-Version: 2.1
Name: cdjs
Version: 0.1.5
Summary: Custom Datetime JSON Serializer
Home-Page: https://github.com/ofhellsfire/cdjs
Author: ofhellsfire <ofhellsfire@yandex.ru>
Author-Email: ofhellsfire <ofhellsfire@yandex.ru>
License: MIT
Requires-Python: >=3.6
